edu_code_mutate.py
edu_code_mutate-0.0.1.dist-info/LICENSE
edu_code_mutate-0.0.1.dist-info/METADATA
edu_code_mutate-0.0.1.dist-info/WHEEL
edu_code_mutate-0.0.1.dist-info/top_level.txt
edu_code_mutate-0.0.1.dist-info/RECORD
