Metadata-Version: 2.1
Name: edu-code-mutate
Version: 0.0.1
Summary: Capstone app
Author: Pranjal Naringrekar
Classifier: Programming Language :: Python :: 3
Classifier: License :: OSI Approved :: MIT License
Classifier: Operating System :: OS Independent
Requires-Python: >=3.6
License-File: LICENSE
